eta/__init__.py
eta/constants.py
eta/classifiers/__init__.py
eta/classifiers/tfslim_classifiers.py
eta/classifiers/vgg16_classifiers.py
eta/classifiers/voting_classifiers.py
eta/core/__init__.py
eta/core/annotations.py
eta/core/builder.py
eta/core/c3d.py
eta/core/cli.py
eta/core/config.py
eta/core/data.py
eta/core/diagram.py
eta/core/events.py
eta/core/features.py
eta/core/frames.py
eta/core/frameutils.py
eta/core/geometry.py
eta/core/gps.py
eta/core/graph.py
eta/core/image.py
eta/core/job.py
eta/core/keypoints.py
eta/core/labels.py
eta/core/learning.py
eta/core/logging.py
eta/core/logo.py
eta/core/metadata.py
eta/core/models.py
eta/core/module.py
eta/core/numutils.py
eta/core/objects.py
eta/core/pipeline.py
eta/core/polylines.py
eta/core/primitives.py
eta/core/serial.py
eta/core/status.py
eta/core/storage.py
eta/core/tfutils.py
eta/core/types.py
eta/core/utils.py
eta/core/vgg16.py
eta/core/video.py
eta/core/web.py
eta/core/ziputils.py
eta/core/datasets/__init__.py
eta/core/datasets/builders.py
eta/core/datasets/labeled_datasets.py
eta/core/datasets/split_methods.py
eta/core/datasets/transformers.py
eta/core/datasets/utils.py
eta/core/datasets/video2image.py
eta/detectors/__init__.py
eta/detectors/efficientdet.py
eta/detectors/tfmodels_detectors.py
eta/detectors/utils.py
eta/detectors/yolo.py
eta/examples/README.md
eta/examples/clean.bash
eta/examples/download_data.py
eta/examples/demo_cats/README.md
eta/examples/demo_cats/detect-classify-cats.json
eta/examples/demo_embed_vgg16/README.md
eta/examples/demo_embed_vgg16/embed_image.py
eta/examples/demo_embed_vgg16/embed_image_direct.py
eta/examples/demo_embed_vgg16/embed_vgg16_module-config.json
eta/examples/demo_embed_vgg16/embed_vgg16_module.bash
eta/examples/demo_embed_vgg16/embed_vgg16_pipeline-config.json
eta/examples/demo_embed_vgg16/embed_video-config.json
eta/examples/demo_embed_vgg16/embed_video.py
eta/examples/demo_image_classifier/README.md
voxel51_eta-0.15.3.dist-info/licenses/LICENSE
voxel51_eta-0.15.3.dist-info/METADATA
voxel51_eta-0.15.3.dist-info/WHEEL
voxel51_eta-0.15.3.dist-info/entry_points.txt
voxel51_eta-0.15.3.dist-info/top_level.txt
voxel51_eta-0.15.3.dist-info/RECORD
