Metadata-Version: 2.4
Name: voxel51-eta
Version: 0.15.3
Summary: Extensible Toolkit for Analytics
Home-page: https://github.com/voxel51/eta
Author: Voxel51, Inc.
Author-email: info@voxel51.com
License: Apache
Classifier: Development Status :: 4 - Beta
Classifier: Intended Audience :: Developers
Classifier: Intended Audience :: Science/Research
Classifier: License :: OSI Approved :: Apache Software License
Classifier: Topic :: Scientific/Engineering :: Artificial Intelligence
Classifier: Topic :: Scientific/Engineering :: Image Processing
Classifier: Topic :: Scientific/Engineering :: Image Recognition
Classifier: Topic :: Scientific/Engineering :: Information Analysis
Classifier: Topic :: Scientific/Engineering :: Visualization
Classifier: Operating System :: MacOS :: MacOS X
Classifier: Operating System :: POSIX :: Linux
Classifier: Operating System :: Microsoft :: Windows
Classifier: Programming Language :: Python :: 3
Classifier: Programming Language :: Python :: 3.9
Classifier: Programming Language :: Python :: 3.10
Classifier: Programming Language :: Python :: 3.11
Requires-Python: >=3.9
License-File: LICENSE
Requires-Dist: argcomplete
Requires-Dist: dill
Requires-Dist: glob2
Requires-Dist: jsonlines
Requires-Dist: numpy
Requires-Dist: packaging
Requires-Dist: paramiko<4,>=3
Requires-Dist: Pillow>=6.2
Requires-Dist: py7zr
Requires-Dist: python-dateutil
Requires-Dist: pytz
Requires-Dist: rarfile
Requires-Dist: requests
Requires-Dist: retrying
Requires-Dist: scikit-image
Requires-Dist: sortedcontainers
Requires-Dist: tabulate
Requires-Dist: tzlocal
Requires-Dist: urllib3
Requires-Dist: opencv-python-headless<5,>=4.1
Provides-Extra: pipeline
Requires-Dist: blockdiag; extra == "pipeline"
Requires-Dist: Sphinx; extra == "pipeline"
Requires-Dist: sphinxcontrib-napoleon; extra == "pipeline"
Provides-Extra: storage
Requires-Dist: azure-identity; extra == "storage"
Requires-Dist: azure-storage-blob>=12.4.0; extra == "storage"
Requires-Dist: boto3>=1.15; extra == "storage"
Requires-Dist: google-api-python-client; extra == "storage"
Requires-Dist: google-cloud-storage>=1.36; extra == "storage"
Requires-Dist: httplib2; extra == "storage"
Requires-Dist: pysftp; extra == "storage"
Dynamic: author
Dynamic: author-email
Dynamic: classifier
Dynamic: description
Dynamic: description-content-type
Dynamic: home-page
Dynamic: license
Dynamic: license-file
Dynamic: provides-extra
Dynamic: requires-dist
Dynamic: requires-python
Dynamic: summary
